univention/admin/rest/__init__.py
univention/admin/rest/async_client.py
univention/admin/rest/client/__init__.py
univention/admin/rest/client/__main__.py
udm_rest_api_client-0.1.2.dist-info/METADATA
udm_rest_api_client-0.1.2.dist-info/WHEEL
udm_rest_api_client-0.1.2.dist-info/entry_points.txt
udm_rest_api_client-0.1.2.dist-info/licenses/LICENSE.txt
udm_rest_api_client-0.1.2.dist-info/RECORD
