Metadata-Version: 2.4
Name: udm-rest-api-client
Version: 0.1.2
Summary: Client library to interact with the Univention Directory Manager (UDM) REST API.
Project-URL: Homepage, https://www.univention.com
Project-URL: Documentation, https://docs.software-univention.de/developer-reference/latest/en/udm/rest-api.html
Project-URL: Repository, https://git.knut.univention.de/univention/dev/libraries/udm-rest-api-client
Project-URL: Source, https://git.knut.univention.de/univention/dev/libraries/udm-rest-api-client
Author-email: Univention Maintainers <packages@univention.de>
License-Expression: AGPL-3.0-only
License-File: LICENSE.txt
Classifier: Development Status :: 4 - Beta
Classifier: Environment :: Web Environment
Classifier: Framework :: AsyncIO
Classifier: Intended Audience :: Developers
Classifier: Intended Audience :: Information Technology
Classifier: License :: OSI Approved :: GNU Affero General Public License v3 or later (AGPLv3+)
Classifier: Operating System :: OS Independent
Classifier: Programming Language :: Python
Classifier: Programming Language :: Python :: 3
Classifier: Programming Language :: Python :: 3 :: Only
Classifier: Programming Language :: Python :: 3.11
Classifier: Programming Language :: Python :: 3.12
Classifier: Programming Language :: Python :: 3.13
Classifier: Topic :: Internet
Classifier: Topic :: Internet :: WWW/HTTP
Classifier: Topic :: Software Development
Classifier: Topic :: Software Development :: Libraries
Classifier: Topic :: Software Development :: Libraries :: Python Modules
Classifier: Typing :: Typed
Requires-Python: >=3.11
Requires-Dist: cachecontrol>=0.14.0
Requires-Dist: typing-extensions>=4.0.0
Requires-Dist: uritemplate>=4.1.1
Provides-Extra: async
Requires-Dist: aiohttp>=3.0.0; extra == 'async'
Provides-Extra: cli
Requires-Dist: python-ldap>=3.0.0; extra == 'cli'
Requires-Dist: requests>=2.0.0; extra == 'cli'
Provides-Extra: dev
Requires-Dist: mypy-extensions>=1.0.0; extra == 'dev'
Requires-Dist: mypy>=1.9.0; extra == 'dev'
Requires-Dist: pytest-asyncio>=1.0.0; extra == 'dev'
Requires-Dist: pytest-cov>=6.1.1; extra == 'dev'
Requires-Dist: pytest>=8.4.0; extra == 'dev'
Requires-Dist: types-requests>=2.0.0; extra == 'dev'
Provides-Extra: sync
Requires-Dist: requests>=2.0.0; extra == 'sync'
